coloredmatrix/__init__.py
coloredmatrix/stylize.py
coloredmatrix-0.0.2.dist-info/METADATA
coloredmatrix-0.0.2.dist-info/WHEEL
coloredmatrix-0.0.2.dist-info/LICENSE
coloredmatrix-0.0.2.dist-info/RECORD
